[
  {
    "url": "https://gvreyeclinic.com",
    "name": "GVR Eye Clinic – Eye Care Tenkasi",
    "snippet": "FOR EMERGENCY +91 8870024305 · OPENING HOURS 09.30am to 01.30pm 05.00pm to 08.30pm · FOR APPOINTMENT +91 8870024305 ...",
    "host_name": "gvreyeclinic.com",
    "rank": 0,
    "date": "",
    "favicon": ""
  },
  {
    "url": "https://www.justdial.com/Tenkasi/GVR-Eye-Hospital-Opticals-Mela-Ratha-Veethi/9999P4633-4633-180118095019-G2A5_BZDET",
    "name": "G.V.R Eye Hospital & Opticals in Mela Ratha Veethi,Tenkasi - Justdial",
    "snippet": "No 56/14, G.V.R Eye Hospital & Opticals, Mela Masi Street, Mela Ratha Veethi ... G.V.R Eye Hospital provides comprehensive contact lens services, including ...",
    "host_name": "www.justdial.com",
    "rank": 1,
    "date": "",
    "favicon": ""
  },
  {
    "url": "https://www.instagram.com/gvr_eyehospital",
    "name": "Gvr Eye Hospital (@gvr_eyehospital) • Instagram photos and videos",
    "snippet": "Your Vision, Our Mission | Advanced Eye Care | 🕶️ Trendy Opticals | Expert Doctors & Personalized Service | Tenkasi | Call Us: 8870024305.",
    "host_name": "www.instagram.com",
    "rank": 2,
    "date": "",
    "favicon": ""
  },
  {
    "url": "https://dialmia.com/tenkasi/gvr-eye-hospital?l_id=15487",
    "name": "GVR Eye Hospital - Dialmia",
    "snippet": "56/14, Mela Masi Veethi S, Tenkasi, Tamil Nadu, India- 627811 · 8870024305 · 8870024305 · gvreyeclinic@gmail.com · gvreyeclinic.com · Working Hours. 9:30 AM to 8: ...",
    "host_name": "dialmia.com",
    "rank": 3,
    "date": "",
    "favicon": ""
  },
  {
    "url": "https://www.justdial.com/Tenkasi/G-V-R-Eye-Hospital-West-Car-Street/9999P4633-4633-230423075530-Y1H2_BZDET",
    "name": "G V R Eye Hospital in West Car Street,Tenkasi - Justdial",
    "snippet": "G V R Eye Hospital in West Car Street,Tenkasi. Top Eye Hospitals in Tenkasi. Rated 4.9 based on 2 Customer Reviews and Ratings with 1 Photos.",
    "host_name": "www.justdial.com",
    "rank": 4,
    "date": "",
    "favicon": ""
  },
  {
    "url": "https://m.facebook.com/profile.php?id=100243335831061",
    "name": "GVR Eye Hospital Tenkasi - Home | Facebook",
    "snippet": "GVR Eye Hospital Tenkasi. Company.",
    "host_name": "m.facebook.com",
    "rank": 5,
    "date": "",
    "favicon": ""
  },
  {
    "url": "https://www.rafaeyecareclinic.com",
    "name": "Rafa Eye Care Clinic",
    "snippet": "Give Rafa a call today to book your appointment. General Treatment. Doctors at Rafa provide everything from annual eye exams to corrective vision surgeries. Our ...",
    "host_name": "www.rafaeyecareclinic.com",
    "rank": 6,
    "date": "",
    "favicon": ""
  },
  {
    "url": "https://www.latrexa.com/hospital/gvr-eye-hospital",
    "name": "GVR Eye Hospital | Contact, Address & Booking - Latrexa",
    "snippet": "GVR Eye Hospital — Tenkasi, Tamil Nadu. Phone, address and map on Latrexa Directory ... GVR Eye Hospital. · Closes 8:30 pm · 088700 24305 088700 24305.",
    "host_name": "www.latrexa.com",
    "rank": 7,
    "date": "",
    "favicon": ""
  },
  {
    "url": "https://www.dragarwal.com/eye-clinic/tenkasi",
    "name": "Best Eye Clinics in Tenkasi - Dr Agarwals Eye Hospital",
    "snippet": "Please contact the team on 9594924144 for exact timings. Are pediatric eye care services available at your Tenkasi clinic?",
    "host_name": "www.dragarwal.com",
    "rank": 8,
    "date": "",
    "favicon": ""
  },
  {
    "url": "https://gvreyeclinic.com/doctor",
    "name": "DOCTOR - GVR Eye Clinic",
    "snippet": "56/14 Gvr Eye Hospital . Mela Masi Street Tenkasi Tirunelveli. Book Appointment Now. HOME · DOCTOR · ABOUT US · TREATMENT · GALLERY · CONTACT · placeholder-661- ...",
    "host_name": "gvreyeclinic.com",
    "rank": 9,
    "date": "",
    "favicon": ""
  }
]